MANIFEST.in
README.rst
setup.py
docs/Makefile
docs/conf.py
docs/index.rst
docs/logintc.rst
logintc/__init__.py
logintc/client.py
logintc.egg-info/PKG-INFO
logintc.egg-info/SOURCES.txt
logintc.egg-info/dependency_links.txt
logintc.egg-info/requires.txt
logintc.egg-info/top_level.txt
logintc/tests/test.py