Metadata-Version: 1.1
Name: logintc
Version: 1.1.9
Summary: API client for LoginTC two-factor authentication.
Home-page: https://github.com/logintc/logintc-python
Author: Cyphercor Inc.
Author-email: support@cyphercor.com
License: LICENSE
Keywords: logintc,two-factor,authentication,security
Platform: UNKNOWN
Classifier: Topic :: Security
Classifier: License :: OSI Approved :: BSD License
